{
  "project_info": {
    "project_number": "495063926935",
    "project_id": "flutter-ios-project",
    "storage_bucket": "flutter-ios-project.firebasestorage.app"
  },
  "client": [
    {
      "client_info": {
        "mobilesdk_app_id": "1:495063926935:android:d63fd57abe3c0a1576c1d2",
        "android_client_info": {
          "package_name": "com.linkdev.iOSFullFlutterApp"
        }
      },
      "oauth_client": [],
      "api_key": [
        {
          "current_key": "AIzaSyA7wHVL4Sx3YhiPfEH2PTxsBME4M-_2pTg"
        }
      ],
      "services": {
        "appinvite_service": {
          "other_platform_oauth_client": []
        }
      }
    }
  ],
  "configuration_version": "1"
}